odoo10_addon_product_packaging_barcode-10.0.1.0.0.99.dev3-py3.8-nspkg.pth
odoo/addons/product_packaging_barcode/README.rst
odoo/addons/product_packaging_barcode/__init__.py
odoo/addons/product_packaging_barcode/__manifest__.py
odoo/addons/product_packaging_barcode/i18n/product_packaging_barcode.pot
odoo/addons/product_packaging_barcode/models/__init__.py
odoo/addons/product_packaging_barcode/models/product_packaging.py
odoo/addons/product_packaging_barcode/readme/CONTRIBUTORS.rst
odoo/addons/product_packaging_barcode/readme/DESCRIPTION.rst
odoo/addons/product_packaging_barcode/readme/USAGE.rst
odoo/addons/product_packaging_barcode/static/description/icon.png
odoo/addons/product_packaging_barcode/static/description/index.html
odoo/addons/product_packaging_barcode/views/product_packaging.xml
odoo10_addon_product_packaging_barcode-10.0.1.0.0.99.dev3.dist-info/METADATA
odoo10_addon_product_packaging_barcode-10.0.1.0.0.99.dev3.dist-info/WHEEL
odoo10_addon_product_packaging_barcode-10.0.1.0.0.99.dev3.dist-info/namespace_packages.txt
odoo10_addon_product_packaging_barcode-10.0.1.0.0.99.dev3.dist-info/top_level.txt
odoo10_addon_product_packaging_barcode-10.0.1.0.0.99.dev3.dist-info/RECORD
